awis/__init__.py
awis/awis.py
awis_py-0.0.2.dist-info/LICENSE
awis_py-0.0.2.dist-info/METADATA
awis_py-0.0.2.dist-info/WHEEL
awis_py-0.0.2.dist-info/top_level.txt
awis_py-0.0.2.dist-info/RECORD
