Metadata-Version: 2.1
Name: awis-py
Version: 0.0.2
Summary: UNKNOWN
Home-page: https://github.com/whistlebee/awis-py
License: UNKNOWN
Platform: UNKNOWN
Requires-Python: >=3.6
Requires-Dist: requests
Requires-Dist: lxml
